DataSciPackage/__init__.py
DataSciPackage/functions.py
DataSciPackage/setup.py
DataSciPackage_Exx1date-0.1.1.dist-info/LICENSE
DataSciPackage_Exx1date-0.1.1.dist-info/METADATA
DataSciPackage_Exx1date-0.1.1.dist-info/WHEEL
DataSciPackage_Exx1date-0.1.1.dist-info/top_level.txt
DataSciPackage_Exx1date-0.1.1.dist-info/RECORD
